azely/__init__.py
azely/api.py
azely/consts.py
azely/location.py
azely/object.py
azely/py.typed
azely/time.py
azely/utils.py
azely-1.0.0.dist-info/METADATA
azely-1.0.0.dist-info/WHEEL
azely-1.0.0.dist-info/licenses/LICENSE
azely-1.0.0.dist-info/RECORD
