Metadata-Version: 2.4
Name: azely
Version: 1.0.0
Summary: Azimuth/elevation calculator for astronomical objects
Project-URL: homepage, https://astropenguin.github.io/azely/1.0.0
Project-URL: repository, https://github.com/astropenguin/azely
Author-email: Akio Taniguchi <taniguchi.akio@gmail.com>
License: MIT License
License-File: LICENSE
Keywords: astronomy,azimuth,elevation,ephemeris,sidereal-time,visibility
Classifier: License :: OSI Approved :: MIT License
Classifier: Programming Language :: Python :: 3
Classifier: Programming Language :: Python :: 3.10
Classifier: Programming Language :: Python :: 3.11
Classifier: Programming Language :: Python :: 3.12
Classifier: Programming Language :: Python :: 3.13
Requires-Python: <3.14,>=3.10
Requires-Dist: astropy<8,>=6
Requires-Dist: dateparser<2,>=1
Requires-Dist: ipinfo<6,>=4
Requires-Dist: matplotlib<4,>=3
Requires-Dist: numpy<3,>=2
Requires-Dist: pandas-stubs<3,>=2
Requires-Dist: pandas<3,>=2
Requires-Dist: python-dateutil<3,>=2
Requires-Dist: timezonefinder<7,>=6
Requires-Dist: tomlkit<1.0,>=0.10
Requires-Dist: typing-extensions<5,>=4
